CHANGELOG.rst
drf_imgproxy/__init__.py
drf_imgproxy/apps.py
drf_imgproxy/serializers.py
drf_imgproxy-1.1.0.dist-info/LICENSE
drf_imgproxy-1.1.0.dist-info/WHEEL
drf_imgproxy-1.1.0.dist-info/METADATA
drf_imgproxy-1.1.0.dist-info/RECORD
