Metadata-Version: 2.1
Name: drf-imgproxy
Version: 1.1.0
Summary: Serialize Django's ImageField into imgproxy URLs for your Django REST Framework APIs to generate thumbnails.
Home-page: https://github.com/viper-development/drf-imgproxy
License: MIT
Keywords: imgproxy,django-rest-framework,django,thumbnailer
Author: VIPER Development UG
Author-email: info@viper.dev
Requires-Python: >=3.6,<4.0
Classifier: Development Status :: 5 - Production/Stable
Classifier: Framework :: Django
Classifier: Framework :: Django :: 2.1
Classifier: Framework :: Django :: 2.2
Classifier: Framework :: Django :: 3.0
Classifier: Framework :: Django :: 3.1
Classifier: License :: OSI Approved :: MIT License
Classifier: Programming Language :: Python :: 3
Classifier: Programming Language :: Python :: 3.6
Classifier: Programming Language :: Python :: 3.7
Classifier: Programming Language :: Python :: 3.8
Classifier: Programming Language :: Python :: 3.9
Classifier: Topic :: Software Development :: Libraries :: Python Modules
Requires-Dist: Django (>=2.1.0)
Requires-Dist: djangorestframework (>=3.9.0)
Project-URL: Repository, https://github.com/viper-development/drf-imgproxy
